{
 "md5": "92189ae91844d57403132b442010a94a",
 "isNamespaced": false,
 "textureGroups": [
  {
   "scaleFactor": 1,
   "atlases": [
    {
     "file": "atlas0.png",
     "textures": [
      {
       "symbol": "_buttonPlus_hit",
       "origin": [
        257.4,
        30
       ],
       "rect": [
        1,
        1,
        290,
        60
       ]
      },
      {
       "symbol": "_buttonCancelMovement_down",
       "origin": [
        62.5,
        62.5
       ],
       "rect": [
        293,
        1,
        125,
        125
       ]
      },
      {
       "symbol": "_buttonCancelMovement_over",
       "origin": [
        62.5,
        62.5
       ],
       "rect": [
        1,
        63,
        125,
        125
       ]
      },
      {
       "symbol": "_buttonCancelMovement_png",
       "origin": [
        62.5,
        62.5
       ],
       "rect": [
        128,
        63,
        125,
        125
       ]
      },
      {
       "symbol": "_buttonCancelMovement_up",
       "origin": [
        62.5,
        62.5
       ],
       "rect": [
        255,
        128,
        125,
        125
       ]
      },
      {
       "symbol": "_buttonConfirmMovement",
       "origin": [
        62.5,
        62.5
       ],
       "rect": [
        382,
        128,
        125,
        125
       ]
      },
      {
       "symbol": "_shopButton_HUD_over",
       "origin": [
        60,
        70.6
       ],
       "rect": [
        1,
        190,
        120,
        128
       ]
      },
      {
       "symbol": "_shopButton_HUD_up",
       "origin": [
        60,
        70.6
       ],
       "rect": [
        123,
        190,
        120,
        128
       ]
      },
      {
       "symbol": "infoBar_bg",
       "origin": [
        100.75,
        38
       ],
       "rect": [
        245,
        255,
        202,
        76
       ]
      },
      {
       "symbol": "_internButton_HUD_up",
       "origin": [
        64,
        54.5
       ],
       "rect": [
        1,
        320,
        131,
        115
       ]
      },
      {
       "symbol": "_internButton_HUD_over",
       "origin": [
        64,
        54.5
       ],
       "rect": [
        134,
        333,
        131,
        115
       ]
      },
      {
       "symbol": "_buttonMissions_HUD_over",
       "origin": [
        60.85,
        50
       ],
       "rect": [
        1,
        437,
        125,
        110
       ]
      },
      {
       "symbol": "_buttonMissions_HUD_up",
       "origin": [
        60.85,
        50
       ],
       "rect": [
        267,
        333,
        125,
        110
       ]
      },
      {
       "symbol": "_shopButton_HUD_down",
       "origin": [
        55,
        65.25
       ],
       "rect": [
        394,
        333,
        110,
        118
       ]
      },
      {
       "symbol": "_level_sphere",
       "origin": [
        53.25,
        58.25
       ],
       "rect": [
        267,
        445,
        107,
        117
       ]
      },
      {
       "symbol": "_xp_bar_hell_BG",
       "origin": [
        82.75,
        37.5
       ],
       "rect": [
        1,
        549,
        166,
        75
       ]
      },
      {
       "symbol": "_xp_bar_heaven_BG",
       "origin": [
        82.75,
        37.5
       ],
       "rect": [
        169,
        564,
        166,
        75
       ]
      },
      {
       "symbol": "_buttonPurgatory_HUD_up",
       "origin": [
        58.05,
        49.25
       ],
       "rect": [
        1,
        626,
        119,
        104
       ]
      },
      {
       "symbol": "_buttonPurgatory_HUD_over",
       "origin": [
        58.05,
        49.25
       ],
       "rect": [
        376,
        453,
        119,
        104
       ]
      },
      {
       "symbol": "_internButton_HUD_down",
       "origin": [
        57.05,
        48.4
       ],
       "rect": [
        376,
        559,
        118,
        103
       ]
      },
      {
       "symbol": "_buttonMissions_HUD_down",
       "origin": [
        56.1,
        45.8
       ],
       "rect": [
        122,
        641,
        116,
        101
       ]
      },
      {
       "symbol": "_buttonPurgatory_HUD_down",
       "origin": [
        53.1,
        44.9
       ],
       "rect": [
        128,
        450,
        109,
        95
       ]
      },
      {
       "symbol": "_buttonSkip_SmallConstruction_png",
       "origin": [
        47,
        47
       ],
       "rect": [
        1,
        732,
        94,
        94
       ]
      },
      {
       "symbol": "_buttonMoveBuilding_png",
       "origin": [
        47,
        47
       ],
       "rect": [
        240,
        641,
        94,
        94
       ]
      },
      {
       "symbol": "_buttonUpgradeBuilding_png",
       "origin": [
        42,
        42
       ],
       "rect": [
        420,
        1,
        84,
        84
       ]
      },
      {
       "symbol": "_buttonContextual_over",
       "origin": [
        42,
        42
       ],
       "rect": [
        336,
        664,
        84,
        84
       ]
      },
      {
       "symbol": "_buttonContextual_up",
       "origin": [
        42,
        42
       ],
       "rect": [
        240,
        737,
        84,
        84
       ]
      },
      {
       "symbol": "_buttonEnterBuilding_png",
       "origin": [
        42,
        42
       ],
       "rect": [
        422,
        664,
        84,
        84
       ]
      },
      {
       "symbol": "_buttonSkip_SmallConstruction_hit",
       "origin": [
        77.5,
        22.5
       ],
       "rect": [
        326,
        750,
        155,
        45
       ]
      },
      {
       "symbol": "_buttonDestroyBuilding_png",
       "origin": [
        41.5,
        41.5
       ],
       "rect": [
        97,
        744,
        83,
        83
       ]
      },
      {
       "symbol": "_xp_bar_heaven_Gauge",
       "origin": [
        0,
        23.5
       ],
       "rect": [
        326,
        797,
        143,
        47
       ]
      },
      {
       "symbol": "_xp_bar_hell_Gauge",
       "origin": [
        143,
        23.5
       ],
       "rect": [
        1,
        829,
        143,
        47
       ]
      },
      {
       "symbol": "_buttonContextual_down",
       "origin": [
        40.5,
        40.3
       ],
       "rect": [
        182,
        823,
        81,
        81
       ]
      },
      {
       "symbol": "_buttonContextt_Hit",
       "origin": [
        37.5,
        37.5
       ],
       "rect": [
        1,
        878,
        75,
        75
       ]
      },
      {
       "symbol": "_bg_gauge",
       "origin": [
        60,
        19
       ],
       "rect": [
        1,
        955,
        120,
        38
       ]
      },
      {
       "symbol": "_gauge",
       "origin": [
        60,
        19
       ],
       "rect": [
        78,
        906,
        120,
        38
       ]
      },
      {
       "symbol": "_gauge_buildingTime",
       "origin": [
        60,
        19
       ],
       "rect": [
        123,
        946,
        120,
        38
       ]
      },
      {
       "symbol": "_infopurgatory_bg",
       "origin": [
        76.25,
        13.75
       ],
       "rect": [
        200,
        906,
        153,
        28
       ]
      },
      {
       "symbol": "_isBuilding_icon",
       "origin": [
        33,
        32
       ],
       "rect": [
        245,
        936,
        66,
        64
       ]
      },
      {
       "symbol": "_genericIcon_Large",
       "origin": [
        32,
        32
       ],
       "rect": [
        313,
        936,
        64,
        64
       ]
      },
      {
       "symbol": "_woodIcon_Medium",
       "origin": [
        28,
        28
       ],
       "rect": [
        182,
        744,
        56,
        56
       ]
      },
      {
       "symbol": "_infohouse_bg",
       "origin": [
        48.75,
        13.75
       ],
       "rect": [
        123,
        986,
        98,
        28
       ]
      },
      {
       "symbol": "_neutralSoulIcon_Large",
       "origin": [
        20.5,
        32
       ],
       "rect": [
        449,
        255,
        41,
        64
       ]
      },
      {
       "symbol": "_hardCurrencyIcon_Medium",
       "origin": [
        24,
        24
       ],
       "rect": [
        265,
        823,
        48,
        48
       ]
      },
      {
       "symbol": "_goldIcon_Medium",
       "origin": [
        24,
        24
       ],
       "rect": [
        315,
        846,
        48,
        48
       ]
      },
      {
       "symbol": "_stoneIcon_Medium",
       "origin": [
        24,
        23.05
       ],
       "rect": [
        365,
        846,
        48,
        47
       ]
      },
      {
       "symbol": "_soulIcon_Small",
       "origin": [
        16,
        16
       ],
       "rect": [
        255,
        63,
        32,
        32
       ]
      },
      {
       "symbol": "_buttonPlus_over",
       "origin": [
        15,
        15
       ],
       "rect": [
        265,
        873,
        30,
        30
       ]
      },
      {
       "symbol": "_buttonPlus_down",
       "origin": [
        15,
        15
       ],
       "rect": [
        146,
        829,
        30,
        30
       ]
      },
      {
       "symbol": "_buttonPlus_upp",
       "origin": [
        15,
        15
       ],
       "rect": [
        146,
        861,
        30,
        30
       ]
      },
      {
       "baseClass": "TextSprite",
       "data": {
        "y": -37.75,
        "text": "99/99",
        "x": -86.65,
        "width": 173.25,
        "font": "52px Arial",
        "align": "center",
        "height": 75.5,
        "wordWrap": 1,
        "color": "#000000"
       },
       "symbol": "_infos_house_txt",
       "origin": [
        0,
        0
       ],
       "rect": [
        128,
        437,
        1,
        1
       ]
      },
      {
       "baseClass": "TextSprite",
       "data": {
        "y": -44.45,
        "text": "X9999",
        "x": -117.65,
        "width": 235.3,
        "font": "76px Arial",
        "align": "center",
        "height": 88.9,
        "wordWrap": 0,
        "color": "#000000"
       },
       "symbol": "_valueChange_txt",
       "origin": [
        0,
        0
       ],
       "rect": [
        131,
        437,
        1,
        1
       ]
      },
      {
       "baseClass": "TextSprite",
       "data": {
        "y": -55.9,
        "text": "99",
        "x": -83.45,
        "width": 166.95,
        "font": "94px _sans",
        "align": "center",
        "height": 111.8,
        "wordWrap": 0,
        "color": "#FFFFFF"
       },
       "symbol": "_level_txt",
       "origin": [
        0,
        0
       ],
       "rect": [
        128,
        440,
        1,
        1
       ]
      },
      {
       "baseClass": "TextSprite",
       "data": {
        "y": -37.75,
        "text": "999/999",
        "x": -147.4,
        "width": 294.75,
        "font": "54px Arial",
        "align": "center",
        "height": 75.5,
        "wordWrap": 1,
        "color": "#000000"
       },
       "symbol": "_infoPurgatory_txt",
       "origin": [
        0,
        0
       ],
       "rect": [
        131,
        440,
        1,
        1
       ]
      },
      {
       "baseClass": "TextSprite",
       "data": {
        "y": -27.15,
        "text": "XXXX",
        "x": -70.4,
        "width": 140.85,
        "font": "45px Arial",
        "align": "center",
        "height": 54.3,
        "wordWrap": 1,
        "color": "#FFFFFF"
       },
       "symbol": "_infoBar_value",
       "origin": [
        0,
        0
       ],
       "rect": [
        128,
        443,
        1,
        1
       ]
      },
      {
       "baseClass": "TextSprite",
       "data": {
        "y": -26.55,
        "text": "99h99m99s",
        "x": -120.65,
        "width": 241.35,
        "font": "44px Arial",
        "align": "center",
        "height": 53.15,
        "wordWrap": 1,
        "color": "#000000"
       },
       "symbol": "_time",
       "origin": [
        0,
        0
       ],
       "rect": [
        131,
        443,
        1,
        1
       ]
      }
     ]
    }
   ]
  }
 ],
 "movies": [
  {
   "layers": [
    {
     "keyframes": [
      {
       "ref": "~ButtonMoveBuilding",
       "tweened": false,
       "duration": 1,
       "index": 0,
       "loc": [
        -90,
        0
       ]
      }
     ],
     "name": "ButtonMoveBuilding"
    },
    {
     "keyframes": [
      {
       "ref": "~ButtonDestroyBuilding",
       "tweened": false,
       "duration": 1,
       "index": 0,
       "loc": [
        90,
        -130
       ]
      }
     ],
     "name": "ButtonCancelConstruction"
    }
   ],
   "id": "BuildingContext"
  },
  {
   "layers": [
    {
     "keyframes": [
      {
       "ref": "~isBuilding_gauge",
       "tweened": false,
       "duration": 1,
       "index": 0,
       "loc": [
        -0.75,
        0
       ]
      }
     ],
     "name": "Gauge"
    },
    {
     "keyframes": [
      {
       "ref": "~ButtonSkip_SmallConstruction",
       "tweened": false,
       "duration": 1,
       "index": 0,
       "loc": [
        90,
        0
       ]
      }
     ],
     "name": "Button"
    }
   ],
   "id": "BuildingTimer"
  },
  {
   "layers": [
    {
     "keyframes": [
      {
       "ref": "~ButtonUpgradeBuilding",
       "tweened": false,
       "duration": 1,
       "index": 0,
       "loc": [
        90,
        0
       ]
      }
     ],
     "name": "ButtonUpgradeBuilding"
    },
    {
     "keyframes": [
      {
       "ref": "~ButtonEnterBuilding",
       "tweened": false,
       "duration": 1,
       "index": 0,
       "loc": [
        -90,
        -130
       ]
      }
     ],
     "name": "EnterButton"
    },
    {
     "keyframes": [
      {
       "ref": "~ButtonDestroyBuilding",
       "tweened": false,
       "duration": 1,
       "index": 0,
       "loc": [
        90,
        -130
       ]
      }
     ],
     "name": "ButtonDestroyBuilding"
    },
    {
     "keyframes": [
      {
       "ref": "~ButtonMoveBuilding",
       "tweened": false,
       "duration": 1,
       "index": 0,
       "loc": [
        -90,
        0
       ]
      }
     ],
     "name": "MoveButton"
    }
   ],
   "id": "BuiltContext"
  },
  {
   "layers": [
    {
     "keyframes": [
      {
       "ref": "SoulsCounter_house",
       "tweened": false,
       "duration": 1,
       "index": 0,
       "loc": [
        10,
        0
       ]
      }
     ],
     "name": "SoulsCounter_House"
    },
    {
     "keyframes": [
      {
       "ref": "~ButtonUpgradeBuilding",
       "tweened": false,
       "duration": 1,
       "index": 0,
       "loc": [
        90,
        0
       ]
      }
     ],
     "name": "ButtonUpgradeBuilding"
    },
    {
     "keyframes": [
      {
       "ref": "~ButtonEnterBuilding",
       "tweened": false,
       "duration": 1,
       "index": 0,
       "loc": [
        -90,
        -130
       ]
      }
     ],
     "name": "EnterButton"
    },
    {
     "keyframes": [
      {
       "ref": "~ButtonDestroyBuilding",
       "tweened": false,
       "duration": 1,
       "index": 0,
       "loc": [
        90,
        -130
       ]
      }
     ],
     "name": "ButtonDestroyBuilding"
    },
    {
     "keyframes": [
      {
       "ref": "~ButtonMoveBuilding",
       "tweened": false,
       "duration": 1,
       "index": 0,
       "loc": [
        -90,
        0
       ]
      }
     ],
     "name": "MoveButton"
    }
   ],
   "id": "BuiltContext_house"
  },
  {
   "layers": [
    {
     "keyframes": [
      {
       "tweened": false,
       "index": 0,
       "loc": [
        -119.475,
        -291.325
       ],
       "ref": "~HUD_Xp_Bar_Heaven",
       "data": {
        "UIPosition": "top",
        "UIPosition_Desktop": "top"
       },
       "duration": 1
      }
     ],
     "name": "HUD_HeavenXP"
    },
    {
     "keyframes": [
      {
       "tweened": false,
       "index": 0,
       "loc": [
        140.475,
        -293.6
       ],
       "ref": "~HUD_Xp_Bar_Hell",
       "data": {
        "UIPosition": "top",
        "UIPosition_Desktop": "top"
       },
       "duration": 1
      }
     ],
     "name": "HUD_HellXP"
    },
    {
     "keyframes": [
      {
       "tweened": false,
       "index": 0,
       "loc": [
        10,
        -285
       ],
       "ref": "~HUD_Level",
       "data": {
        "UIPosition": "top",
        "UIPosition_Desktop": "top"
       },
       "duration": 1
      }
     ],
     "name": "HUD_Level"
    },
    {
     "keyframes": [
      {
       "tweened": false,
       "index": 0,
       "loc": [
        -395,
        -295
       ],
       "ref": "~INFO_HardCurrency",
       "data": {
        "UIPosition": "topRight",
        "UIPosition_Desktop": "top"
       },
       "duration": 1
      }
     ],
     "name": "HUD_HardCurrency"
    },
    {
     "keyframes": [
      {
       "tweened": false,
       "index": 0,
       "loc": [
        395,
        -295
       ],
       "ref": "~INFO_SoftCurrency",
       "data": {
        "UIPosition": "topRight",
        "UIPosition_Desktop": "top"
       },
       "duration": 1
      }
     ],
     "name": "HUD_SoftCurrency"
    },
    {
     "keyframes": [
      {
       "tweened": false,
       "index": 0,
       "loc": [
        -435.75,
        260.15
       ],
       "ref": "~ButtonShop_HUD",
       "data": {
        "UIPosition": "bottomLeft",
        "UIPosition_Desktop": "bottom"
       },
       "duration": 1
      }
     ],
     "name": "ButtonShop_HUD"
    },
    {
     "keyframes": [
      {
       "tweened": false,
       "index": 0,
       "loc": [
        431.7,
        114.75
       ],
       "ref": "~ButtonMissions_HUD",
       "data": {
        "UIPosition": "bottomRight",
        "UIPosition_Desktop": "bottom"
       },
       "duration": 1
      }
     ],
     "name": "ButtonMissions_HUD"
    },
    {
     "keyframes": [
      {
       "tweened": false,
       "index": 0,
       "loc": [
        -437.7,
        120
       ],
       "ref": "~ButtonPurgatory_HUD",
       "data": {
        "UIPosition": "bottomLeft",
        "UIPosition_Desktop": "bottom"
       },
       "duration": 1
      }
     ],
     "name": "HUD_PurgatoryButton"
    },
    {
     "keyframes": [
      {
       "tweened": false,
       "index": 0,
       "loc": [
        428.775,
        257.5
       ],
       "ref": "~ButtonsInterns_HUD",
       "data": {
        "UIPosition": "bottomRight",
        "UIPosition_Desktop": "bottom"
       },
       "duration": 1
      }
     ],
     "name": "HUD_InternsButton"
    }
   ],
   "id": "HUD"
  },
  {
   "layers": [
    {
     "keyframes": [
      {
       "tweened": false,
       "index": 0,
       "loc": [
        -129.925,
        -290.65
       ],
       "ref": "~HUD_Xp_Bar_Heaven",
       "data": {
        "UIPosition": "top",
        "UIPosition_Desktop": "top"
       },
       "duration": 1
      }
     ],
     "name": "HUD_HeavenXP"
    },
    {
     "keyframes": [
      {
       "tweened": false,
       "index": 0,
       "loc": [
        131.5,
        -292.075
       ],
       "ref": "~HUD_Xp_Bar_Hell",
       "data": {
        "UIPosition": "top",
        "UIPosition_Desktop": "top"
       },
       "duration": 1
      }
     ],
     "name": "HUD_HellXP"
    },
    {
     "keyframes": [
      {
       "tweened": false,
       "index": 0,
       "loc": [
        0,
        -285
       ],
       "ref": "~HUD_Level",
       "data": {
        "UIPosition": "top",
        "UIPosition_Desktop": "top"
       },
       "duration": 1
      }
     ],
     "name": "HUD_Level"
    },
    {
     "keyframes": [
      {
       "tweened": false,
       "index": 0,
       "loc": [
        395,
        -212.8
       ],
       "ref": "~INFO_HardCurrency",
       "data": {
        "UIPosition": "topRight",
        "UIPosition_Desktop": "top"
       },
       "duration": 1
      }
     ],
     "name": "HUD_HardCurrency"
    },
    {
     "keyframes": [
      {
       "tweened": false,
       "index": 0,
       "loc": [
        395,
        -292.8
       ],
       "ref": "~INFO_SoftCurrency",
       "data": {
        "UIPosition": "topRight",
        "UIPosition_Desktop": "top"
       },
       "duration": 1
      }
     ],
     "name": "HUD_SoftCurrency"
    },
    {
     "keyframes": [
      {
       "tweened": false,
       "index": 0,
       "loc": [
        -395,
        -292.8
       ],
       "ref": "~INFO_Wood",
       "data": {
        "UIPosition": "topRight",
        "UIPosition_Desktop": "top"
       },
       "duration": 1
      }
     ],
     "name": "HUD_Wood"
    },
    {
     "keyframes": [
      {
       "tweened": false,
       "index": 0,
       "loc": [
        -395,
        -212.8
       ],
       "ref": "~INFO_Iron",
       "data": {
        "UIPosition": "topRight",
        "UIPosition_Desktop": "top"
       },
       "duration": 1
      }
     ],
     "name": "HUD_Iron"
    },
    {
     "keyframes": [
      {
       "tweened": false,
       "index": 0,
       "loc": [
        -440.475,
        273.7
       ],
       "ref": "~ButtonShop_HUD",
       "data": {
        "UIPosition": "bottomLeft",
        "UIPosition_Desktop": "bottom"
       },
       "duration": 1
      }
     ],
     "name": "ButtonShop_HUD"
    },
    {
     "keyframes": [
      {
       "tweened": false,
       "index": 0,
       "loc": [
        281.1,
        271.875
       ],
       "ref": "~ButtonMissions_HUD",
       "data": {
        "UIPosition": "bottomRight",
        "UIPosition_Desktop": "bottom"
       },
       "duration": 1
      }
     ],
     "name": "ButtonMissions_HUD"
    },
    {
     "keyframes": [
      {
       "tweened": false,
       "index": 0,
       "loc": [
        -287.925,
        277.125
       ],
       "ref": "~ButtonPurgatory_HUD",
       "data": {
        "UIPosition": "bottomLeft",
        "UIPosition_Desktop": "bottom"
       },
       "duration": 1
      }
     ],
     "name": "HUD_PurgatoryButton"
    },
    {
     "keyframes": [
      {
       "tweened": false,
       "index": 0,
       "loc": [
        428.775,
        271.05
       ],
       "ref": "~ButtonsInterns_HUD",
       "data": {
        "UIPosition": "bottomRight",
        "UIPosition_Desktop": "bottom"
       },
       "duration": 1
      }
     ],
     "name": "HUD_InternsButton"
    }
   ],
   "id": "HUD_Desktop"
  },
  {
   "layers": [
    {
     "keyframes": [
      {
       "ref": "~ButtonCancelMovement",
       "tweened": false,
       "duration": 1,
       "index": 0
      }
     ],
     "name": "Layer 1"
    }
   ],
   "id": "MoveBuilding_Desktop"
  },
  {
   "layers": [
    {
     "keyframes": [
      {
       "ref": "~ButtonConfirmMovement",
       "tweened": false,
       "duration": 1,
       "index": 0,
       "loc": [
        50,
        0.25
       ]
      }
     ],
     "name": "Button_ConfirmMovement"
    },
    {
     "keyframes": [
      {
       "ref": "~ButtonCancelMovement",
       "tweened": false,
       "duration": 1,
       "index": 0,
       "loc": [
        -50,
        0.125
       ]
      }
     ],
     "name": "Button_CancelMovement"
    }
   ],
   "id": "MovingBuilding"
  },
  {
   "layers": [
    {
     "keyframes": [
      {
       "pivot": [
        32,
        32
       ],
       "index": 0,
       "loc": [
        0,
        32
       ],
       "ref": "_genericIcon_Large",
       "tweened": false,
       "duration": 1
      }
     ],
     "name": "_currency"
    }
   ],
   "data": {
    "UIPosition": "top",
    "UI": ""
   },
   "id": "ProdDone"
  },
  {
   "layers": [
    {
     "keyframes": [
      {
       "ref": "~isProducing_gauge",
       "tweened": false,
       "duration": 1,
       "index": 0,
       "loc": [
        -1.525,
        2.475
       ]
      }
     ],
     "name": "Gauge"
    },
    {
     "keyframes": [
      {
       "duration": 1,
       "index": 0
      }
     ],
     "name": "Icon"
    }
   ],
   "id": "ProducingTimer"
  },
  {
   "layers": [
    {
     "keyframes": [
      {
       "pivot": [
        48.75,
        13.75
       ],
       "index": 0,
       "loc": [
        -5.7,
        -1.275
       ],
       "ref": "_infohouse_bg",
       "tweened": false,
       "duration": 1
      }
     ],
     "name": "BG"
    },
    {
     "keyframes": [
      {
       "ref": "_infos_house_txt",
       "tweened": false,
       "duration": 1,
       "index": 0,
       "loc": [
        -0.25,
        2.5
       ]
      }
     ],
     "name": "_infos_house_txt"
    },
    {
     "keyframes": [
      {
       "pivot": [
        16,
        16
       ],
       "index": 0,
       "loc": [
        -54.425,
        -0.275
       ],
       "ref": "_soulIcon_Small",
       "tweened": false,
       "duration": 1
      }
     ],
     "name": "_infos_house_icon"
    }
   ],
   "id": "SoulsCounter_house"
  },
  {
   "layers": [
    {
     "keyframes": [
      {
       "pivot": [
        76.25,
        13.75
       ],
       "index": 0,
       "loc": [
        -6.425,
        0
       ],
       "ref": "_infopurgatory_bg",
       "tweened": false,
       "duration": 1
      }
     ],
     "name": "BG"
    },
    {
     "keyframes": [
      {
       "ref": "_infoPurgatory_txt",
       "tweened": false,
       "duration": 1,
       "index": 0,
       "loc": [
        -8.8,
        3.2
       ]
      }
     ],
     "name": "_infos_purgatory_txt"
    },
    {
     "keyframes": [
      {
       "pivot": [
        20.475,
        32
       ],
       "index": 0,
       "loc": [
        -91.65,
        -9.925
       ],
       "ref": "_neutralSoulIcon_Large",
       "tweened": false,
       "duration": 1
      }
     ],
     "name": "_infos_purgatory_icon"
    }
   ],
   "id": "SoulsCounter_purgatory"
  },
  {
   "layers": [
    {
     "keyframes": [
      {
       "ref": "_valueChange_txt",
       "tweened": false,
       "duration": 1,
       "index": 0
      }
     ],
     "name": "value"
    },
    {
     "keyframes": [
      {
       "pivot": [
        32,
        32
       ],
       "index": 0,
       "loc": [
        90.775,
        0
       ],
       "ref": "_genericIcon_Large",
       "tweened": false,
       "duration": 1
      }
     ],
     "name": "icon"
    }
   ],
   "data": {
    "y": -48.35,
    "text": "+999",
    "color": "#000000",
    "width": 191.75,
    "font": "83px _sans",
    "height": 96.75,
    "wordWrap": 0,
    "x": -95.85
   },
   "id": "ValueChange"
  },
  {
   "layers": [
    {
     "keyframes": [
      {
       "ref": "_buttonCancelMovement_up",
       "pivot": [
        62.5,
        62.5
       ],
       "tweened": false,
       "duration": 1,
       "index": 0
      },
      {
       "tweened": false,
       "tint": [
        0.35,
        "#7DD0FF"
       ],
       "index": 1,
       "ref": "_buttonCancelMovement_over",
       "pivot": [
        62.5,
        62.5
       ],
       "duration": 1
      },
      {
       "ref": "_buttonCancelMovement_down",
       "pivot": [
        62.5,
        62.5
       ],
       "tweened": false,
       "duration": 2,
       "index": 2
      }
     ],
     "name": "Layer 1"
    },
    {
     "keyframes": [
      {
       "pivot": [
        62.5,
        62.475
       ],
       "index": 0,
       "loc": [
        0,
        -0.025
       ],
       "ref": "_buttonCancelMovement_png",
       "tweened": false,
       "duration": 4
      }
     ],
     "name": "cancel-music.png"
    }
   ],
   "id": "~ButtonCancelMovement",
   "baseClass": "flash.display.SimpleButton"
  },
  {
   "layers": [
    {
     "keyframes": [
      {
       "ref": "_buttonCancelMovement_up",
       "pivot": [
        62.5,
        62.5
       ],
       "tweened": false,
       "duration": 1,
       "index": 0
      },
      {
       "tweened": false,
       "tint": [
        0.35,
        "#7DD0FF"
       ],
       "index": 1,
       "ref": "_buttonCancelMovement_over",
       "pivot": [
        62.5,
        62.5
       ],
       "duration": 1
      },
      {
       "ref": "_buttonCancelMovement_down",
       "pivot": [
        62.5,
        62.5
       ],
       "tweened": false,
       "duration": 2,
       "index": 2
      }
     ],
     "name": "Layer 1"
    },
    {
     "keyframes": [
      {
       "pivot": [
        62.5,
        62.5
       ],
       "index": 0,
       "loc": [
        0,
        -0.25
       ],
       "ref": "_buttonConfirmMovement",
       "tweened": false,
       "duration": 4
      }
     ],
     "name": "checked.png"
    }
   ],
   "id": "~ButtonConfirmMovement",
   "baseClass": "flash.display.SimpleButton"
  },
  {
   "layers": [
    {
     "keyframes": [
      {
       "ref": "_buttonContextual_up",
       "pivot": [
        42,
        42
       ],
       "tweened": false,
       "duration": 1,
       "index": 0
      },
      {
       "tweened": false,
       "tint": [
        0.3,
        "#7DD0FF"
       ],
       "index": 1,
       "ref": "_buttonContextual_over",
       "pivot": [
        42,
        42
       ],
       "duration": 1
      },
      {
       "ref": "_buttonContextual_down",
       "pivot": [
        40.5,
        40.3
       ],
       "tweened": false,
       "duration": 1,
       "index": 2
      },
      {
       "ref": "_buttonContextt_Hit",
       "pivot": [
        37.5,
        37.5
       ],
       "tweened": false,
       "duration": 1,
       "index": 3
      }
     ],
     "name": "Layer 1"
    },
    {
     "keyframes": [
      {
       "ref": "_buttonDestroyBuilding_png",
       "pivot": [
        41.5,
        41.5
       ],
       "tweened": false,
       "duration": 1,
       "index": 0
      },
      {
       "ref": "_buttonDestroyBuilding_png",
       "pivot": [
        41.5,
        41.5
       ],
       "tweened": false,
       "duration": 1,
       "index": 1
      },
      {
       "tweened": false,
       "index": 2,
       "ref": "_buttonDestroyBuilding_png",
       "pivot": [
        41.5,
        41.5
       ],
       "scale": [
        0.9639,
        0.9639
       ],
       "duration": 1
      },
      {
       "ref": "_buttonDestroyBuilding_png",
       "pivot": [
        41.5,
        41.5
       ],
       "tweened": false,
       "duration": 1,
       "index": 3
      }
     ],
     "name": "enter.png"
    }
   ],
   "id": "~ButtonDestroyBuilding",
   "baseClass": "flash.display.SimpleButton"
  },
  {
   "layers": [
    {
     "keyframes": [
      {
       "ref": "_buttonContextual_up",
       "pivot": [
        42,
        42
       ],
       "tweened": false,
       "duration": 1,
       "index": 0
      },
      {
       "tweened": false,
       "tint": [
        0.3,
        "#7DD0FF"
       ],
       "index": 1,
       "ref": "_buttonContextual_over",
       "pivot": [
        42,
        42
       ],
       "duration": 1
      },
      {
       "ref": "_buttonContextual_down",
       "pivot": [
        40.5,
        40.3
       ],
       "tweened": false,
       "duration": 1,
       "index": 2
      },
      {
       "ref": "_buttonContextt_Hit",
       "pivot": [
        37.5,
        37.5
       ],
       "tweened": false,
       "duration": 1,
       "index": 3
      }
     ],
     "name": "Layer 1"
    },
    {
     "keyframes": [
      {
       "pivot": [
        42,
        42
       ],
       "index": 0,
       "loc": [
        0,
        0.725
       ],
       "ref": "_buttonEnterBuilding_png",
       "tweened": false,
       "duration": 1
      },
      {
       "pivot": [
        42,
        42
       ],
       "index": 1,
       "loc": [
        0,
        0.725
       ],
       "ref": "_buttonEnterBuilding_png",
       "tweened": false,
       "duration": 1
      },
      {
       "pivot": [
        42,
        42
       ],
       "index": 2,
       "loc": [
        0,
        0.725
       ],
       "ref": "_buttonEnterBuilding_png",
       "tweened": false,
       "scale": [
        0.9518,
        0.9518
       ],
       "duration": 1
      },
      {
       "pivot": [
        42,
        42
       ],
       "index": 3,
       "loc": [
        0,
        0.725
       ],
       "ref": "_buttonEnterBuilding_png",
       "tweened": false,
       "duration": 1
      }
     ],
     "name": "enter.png"
    }
   ],
   "id": "~ButtonEnterBuilding",
   "baseClass": "flash.display.SimpleButton"
  },
  {
   "layers": [
    {
     "keyframes": [
      {
       "ref": "_buttonMissions_HUD_up",
       "pivot": [
        60.85,
        50
       ],
       "tweened": false,
       "duration": 1,
       "index": 0
      },
      {
       "tweened": false,
       "tint": [
        0.35,
        "#7DD0FF"
       ],
       "index": 1,
       "ref": "_buttonMissions_HUD_over",
       "pivot": [
        60.85,
        50
       ],
       "duration": 1
      },
      {
       "ref": "_buttonMissions_HUD_down",
       "pivot": [
        56.075,
        45.825
       ],
       "tweened": false,
       "duration": 2,
       "index": 2
      }
     ],
     "name": "Button"
    }
   ],
   "id": "~ButtonMissions_HUD",
   "baseClass": "flash.display.SimpleButton"
  },
  {
   "layers": [
    {
     "keyframes": [
      {
       "ref": "_buttonContextual_up",
       "pivot": [
        42,
        42
       ],
       "tweened": false,
       "duration": 1,
       "index": 0
      },
      {
       "tweened": false,
       "tint": [
        0.3,
        "#7DD0FF"
       ],
       "index": 1,
       "ref": "_buttonContextual_over",
       "pivot": [
        42,
        42
       ],
       "duration": 1
      },
      {
       "ref": "_buttonContextual_down",
       "pivot": [
        40.5,
        40.3
       ],
       "tweened": false,
       "duration": 1,
       "index": 2
      },
      {
       "ref": "_buttonContextt_Hit",
       "pivot": [
        37.5,
        37.5
       ],
       "tweened": false,
       "duration": 1,
       "index": 3
      }
     ],
     "name": "Layer 1"
    },
    {
     "keyframes": [
      {
       "pivot": [
        47,
        47
       ],
       "index": 0,
       "loc": [
        0,
        1.5
       ],
       "ref": "_buttonMoveBuilding_png",
       "tweened": false,
       "duration": 1
      },
      {
       "pivot": [
        47,
        47
       ],
       "index": 1,
       "loc": [
        0,
        1.5
       ],
       "ref": "_buttonMoveBuilding_png",
       "tweened": false,
       "duration": 1
      },
      {
       "pivot": [
        47,
        47
       ],
       "index": 2,
       "loc": [
        0,
        1.5
       ],
       "ref": "_buttonMoveBuilding_png",
       "tweened": false,
       "scale": [
        0.9468,
        0.9468
       ],
       "duration": 1
      },
      {
       "pivot": [
        47,
        47
       ],
       "index": 3,
       "loc": [
        0,
        1.5
       ],
       "ref": "_buttonMoveBuilding_png",
       "tweened": false,
       "duration": 1
      }
     ],
     "name": "move-option.png"
    }
   ],
   "id": "~ButtonMoveBuilding",
   "baseClass": "flash.display.SimpleButton"
  },
  {
   "layers": [
    {
     "keyframes": [
      {
       "ref": "_buttonPlus_upp",
       "pivot": [
        15,
        15
       ],
       "tweened": false,
       "duration": 1,
       "index": 0
      },
      {
       "ref": "_buttonPlus_over",
       "pivot": [
        15,
        15
       ],
       "tweened": false,
       "duration": 1,
       "index": 1
      },
      {
       "tweened": false,
       "index": 2,
       "ref": "_buttonPlus_down",
       "pivot": [
        15,
        15
       ],
       "scale": [
        0.9333,
        0.9333
       ],
       "duration": 1
      },
      {
       "ref": "_buttonPlus_hit",
       "pivot": [
        257.375,
        30
       ],
       "tweened": false,
       "duration": 1,
       "index": 3
      }
     ],
     "name": "Layer 1"
    }
   ],
   "id": "~ButtonPlus",
   "baseClass": "flash.display.SimpleButton"
  },
  {
   "layers": [
    {
     "keyframes": [
      {
       "ref": "_buttonPurgatory_HUD_up",
       "pivot": [
        58.05,
        49.25
       ],
       "tweened": false,
       "duration": 1,
       "index": 0
      },
      {
       "tweened": false,
       "tint": [
        0.35,
        "#7DD0FF"
       ],
       "index": 1,
       "ref": "_buttonPurgatory_HUD_over",
       "pivot": [
        58.05,
        49.25
       ],
       "duration": 1
      },
      {
       "ref": "_buttonPurgatory_HUD_down",
       "pivot": [
        53.075,
        44.9
       ],
       "tweened": false,
       "duration": 2,
       "index": 2
      }
     ],
     "name": "Button"
    }
   ],
   "id": "~ButtonPurgatory_HUD",
   "baseClass": "flash.display.SimpleButton"
  },
  {
   "layers": [
    {
     "keyframes": [
      {
       "ref": "_shopButton_HUD_up",
       "pivot": [
        60,
        70.6
       ],
       "tweened": false,
       "duration": 1,
       "index": 0
      },
      {
       "tweened": false,
       "tint": [
        0.35,
        "#7DD0FF"
       ],
       "index": 1,
       "ref": "_shopButton_HUD_over",
       "pivot": [
        60,
        70.6
       ],
       "duration": 1
      },
      {
       "ref": "_shopButton_HUD_down",
       "pivot": [
        55,
        65.25
       ],
       "tweened": false,
       "duration": 2,
       "index": 2
      }
     ],
     "name": "Button"
    }
   ],
   "id": "~ButtonShop_HUD",
   "baseClass": "flash.display.SimpleButton"
  },
  {
   "layers": [
    {
     "keyframes": [
      {
       "ref": "_buttonContextual_up",
       "pivot": [
        42,
        42
       ],
       "tweened": false,
       "duration": 1,
       "index": 0
      },
      {
       "tweened": false,
       "tint": [
        0.3,
        "#7DD0FF"
       ],
       "index": 1,
       "ref": "_buttonContextual_over",
       "pivot": [
        42,
        42
       ],
       "duration": 1
      },
      {
       "ref": "_buttonContextual_down",
       "pivot": [
        40.5,
        40.3
       ],
       "tweened": false,
       "duration": 1,
       "index": 2
      },
      {
       "pivot": [
        77.5,
        22.5
       ],
       "index": 3,
       "loc": [
        -52.5,
        0
       ],
       "ref": "_buttonSkip_SmallConstruction_hit",
       "tweened": false,
       "duration": 1
      }
     ],
     "name": "Layer 1"
    },
    {
     "keyframes": [
      {
       "pivot": [
        47,
        47
       ],
       "index": 0,
       "loc": [
        -0.5,
        0
       ],
       "ref": "_buttonSkip_SmallConstruction_png",
       "tweened": false,
       "duration": 1
      },
      {
       "pivot": [
        47,
        47
       ],
       "index": 1,
       "loc": [
        -0.5,
        0
       ],
       "ref": "_buttonSkip_SmallConstruction_png",
       "tweened": false,
       "duration": 1
      },
      {
       "pivot": [
        47,
        47
       ],
       "index": 2,
       "loc": [
        -0.5,
        0
       ],
       "ref": "_buttonSkip_SmallConstruction_png",
       "tweened": false,
       "scale": [
        0.9468,
        0.9468
       ],
       "duration": 1
      },
      {
       "pivot": [
        47,
        47
       ],
       "index": 3,
       "loc": [
        -0.5,
        0
       ],
       "ref": "_buttonSkip_SmallConstruction_png",
       "tweened": false,
       "duration": 1
      }
     ],
     "name": "fast-foward-arrows.png"
    },
    {
     "keyframes": [
      {
       "duration": 4,
       "index": 0
      }
     ],
     "name": "Icon_HardCurrency"
    },
    {
     "keyframes": [
      {
       "duration": 4,
       "index": 0
      }
     ],
     "name": "Text_HardPrice"
    }
   ],
   "id": "~ButtonSkip_SmallConstruction",
   "baseClass": "flash.display.SimpleButton"
  },
  {
   "layers": [
    {
     "keyframes": [
      {
       "ref": "_buttonContextual_up",
       "pivot": [
        42,
        42
       ],
       "tweened": false,
       "duration": 1,
       "index": 0
      },
      {
       "tweened": false,
       "tint": [
        0.3,
        "#7DD0FF"
       ],
       "index": 1,
       "ref": "_buttonContextual_over",
       "pivot": [
        42,
        42
       ],
       "duration": 1
      },
      {
       "ref": "_buttonContextual_down",
       "pivot": [
        40.5,
        40.3
       ],
       "tweened": false,
       "duration": 1,
       "index": 2
      },
      {
       "ref": "_buttonContextt_Hit",
       "pivot": [
        37.5,
        37.5
       ],
       "tweened": false,
       "duration": 1,
       "index": 3
      }
     ],
     "name": "Layer 1"
    },
    {
     "keyframes": [
      {
       "ref": "_buttonUpgradeBuilding_png",
       "pivot": [
        42,
        42
       ],
       "tweened": false,
       "duration": 1,
       "index": 0
      },
      {
       "ref": "_buttonUpgradeBuilding_png",
       "pivot": [
        42,
        42
       ],
       "tweened": false,
       "duration": 1,
       "index": 1
      },
      {
       "tweened": false,
       "index": 2,
       "ref": "_buttonUpgradeBuilding_png",
       "pivot": [
        42,
        42
       ],
       "scale": [
        0.9524,
        0.9524
       ],
       "duration": 1
      },
      {
       "ref": "_buttonUpgradeBuilding_png",
       "pivot": [
        42,
        42
       ],
       "tweened": false,
       "duration": 1,
       "index": 3
      }
     ],
     "name": "enter.png"
    }
   ],
   "id": "~ButtonUpgradeBuilding",
   "baseClass": "flash.display.SimpleButton"
  },
  {
   "layers": [
    {
     "keyframes": [
      {
       "ref": "_internButton_HUD_up",
       "pivot": [
        64.025,
        54.525
       ],
       "tweened": false,
       "duration": 1,
       "index": 0
      },
      {
       "tweened": false,
       "tint": [
        0.35,
        "#7DD0FF"
       ],
       "index": 1,
       "ref": "_internButton_HUD_over",
       "pivot": [
        64.025,
        54.525
       ],
       "duration": 1
      },
      {
       "ref": "_internButton_HUD_down",
       "pivot": [
        57.05,
        48.425
       ],
       "tweened": false,
       "duration": 2,
       "index": 2
      }
     ],
     "name": "Button"
    }
   ],
   "id": "~ButtonsInterns_HUD",
   "baseClass": "flash.display.SimpleButton"
  },
  {
   "layers": [
    {
     "keyframes": [
      {
       "ref": "_level_sphere",
       "pivot": [
        53.25,
        58.25
       ],
       "tweened": false,
       "duration": 1,
       "index": 0
      }
     ],
     "name": "Sphere"
    },
    {
     "keyframes": [
      {
       "ref": "_level_txt",
       "tweened": false,
       "duration": 1,
       "index": 0
      }
     ],
     "name": "_level_txt"
    }
   ],
   "id": "~HUD_Level"
  },
  {
   "layers": [
    {
     "keyframes": [
      {
       "pivot": [
        82.75,
        37.5
       ],
       "index": 0,
       "loc": [
        -1.55,
        0.775
       ],
       "ref": "_xp_bar_heaven_BG",
       "tweened": false,
       "duration": 1
      }
     ],
     "name": "bgGauge"
    },
    {
     "keyframes": [
      {
       "pivot": [
        0,
        23.5
       ],
       "index": 0,
       "loc": [
        -61.05,
        1.375
       ],
       "ref": "_xp_bar_heaven_Gauge",
       "tweened": false,
       "duration": 1
      }
     ],
     "name": "movingGauge"
    },
    {
     "keyframes": [
      {
       "duration": 1,
       "index": 0
      }
     ],
     "name": "Hud_xp_txt"
    }
   ],
   "id": "~HUD_Xp_Bar_Heaven"
  },
  {
   "layers": [
    {
     "keyframes": [
      {
       "pivot": [
        82.75,
        37.5
       ],
       "index": 0,
       "loc": [
        0,
        5
       ],
       "ref": "_xp_bar_hell_BG",
       "tweened": false,
       "duration": 1
      }
     ],
     "name": "bgGauge"
    },
    {
     "keyframes": [
      {
       "pivot": [
        143,
        23.5
       ],
       "index": 0,
       "loc": [
        60.25,
        2.4
       ],
       "ref": "_xp_bar_hell_Gauge",
       "tweened": false,
       "duration": 1
      }
     ],
     "name": "movingGauge"
    },
    {
     "keyframes": [
      {
       "duration": 1,
       "index": 0
      }
     ],
     "name": "Hud_xp_txt"
    }
   ],
   "id": "~HUD_Xp_Bar_Hell"
  },
  {
   "layers": [
    {
     "keyframes": [
      {
       "ref": "infoBar_bg",
       "pivot": [
        100.75,
        38
       ],
       "tweened": false,
       "duration": 1,
       "index": 0
      }
     ],
     "name": "bar_bg"
    },
    {
     "keyframes": [
      {
       "ref": "_infoBar_value",
       "tweened": false,
       "duration": 1,
       "index": 0
      }
     ],
     "name": "bar_txt"
    },
    {
     "keyframes": [
      {
       "pivot": [
        24,
        24
       ],
       "index": 0,
       "loc": [
        -76.75,
        0
       ],
       "ref": "_hardCurrencyIcon_Medium",
       "tweened": false,
       "duration": 1
      }
     ],
     "name": "_icon_hardcurrency"
    },
    {
     "keyframes": [
      {
       "ref": "~ButtonPlus",
       "tweened": false,
       "duration": 1,
       "index": 0,
       "loc": [
        77.5,
        0
       ]
      }
     ],
     "name": "ButtonPlusHC"
    }
   ],
   "id": "~INFO_HardCurrency"
  },
  {
   "layers": [
    {
     "keyframes": [
      {
       "ref": "infoBar_bg",
       "pivot": [
        100.75,
        38
       ],
       "tweened": false,
       "duration": 1,
       "index": 0
      }
     ],
     "name": "bar_bg"
    },
    {
     "keyframes": [
      {
       "pivot": [
        24,
        23.05
       ],
       "index": 0,
       "loc": [
        -81.5,
        0
       ],
       "ref": "_stoneIcon_Medium",
       "tweened": false,
       "duration": 1
      }
     ],
     "name": "_icon_stone"
    },
    {
     "keyframes": [
      {
       "ref": "_infoBar_value",
       "tweened": false,
       "duration": 1,
       "index": 0
      }
     ],
     "name": "bar_txt"
    },
    {
     "keyframes": [
      {
       "ref": "~ButtonPlus",
       "tweened": false,
       "duration": 1,
       "index": 0,
       "loc": [
        77.5,
        0
       ]
      }
     ],
     "name": "ButtonPlusIRON"
    }
   ],
   "id": "~INFO_Iron"
  },
  {
   "layers": [
    {
     "keyframes": [
      {
       "ref": "infoBar_bg",
       "pivot": [
        100.75,
        38
       ],
       "tweened": false,
       "duration": 1,
       "index": 0
      }
     ],
     "name": "bar_bg"
    },
    {
     "keyframes": [
      {
       "pivot": [
        24,
        24
       ],
       "index": 0,
       "loc": [
        -76.75,
        0
       ],
       "ref": "_goldIcon_Medium",
       "tweened": false,
       "duration": 1
      }
     ],
     "name": "_icon_softcurrency"
    },
    {
     "keyframes": [
      {
       "ref": "_infoBar_value",
       "tweened": false,
       "duration": 1,
       "index": 0
      }
     ],
     "name": "bar_txt"
    },
    {
     "keyframes": [
      {
       "ref": "~ButtonPlus",
       "tweened": false,
       "duration": 1,
       "index": 0,
       "loc": [
        77.5,
        0
       ]
      }
     ],
     "name": "ButtonPlusSC"
    }
   ],
   "id": "~INFO_SoftCurrency"
  },
  {
   "layers": [
    {
     "keyframes": [
      {
       "ref": "infoBar_bg",
       "pivot": [
        100.75,
        38
       ],
       "tweened": false,
       "duration": 1,
       "index": 0
      }
     ],
     "name": "bar_bg"
    },
    {
     "keyframes": [
      {
       "pivot": [
        28,
        28
       ],
       "index": 0,
       "loc": [
        -80,
        -5
       ],
       "ref": "_woodIcon_Medium",
       "tweened": false,
       "duration": 1
      }
     ],
     "name": "_icon_wood"
    },
    {
     "keyframes": [
      {
       "ref": "_infoBar_value",
       "tweened": false,
       "duration": 1,
       "index": 0
      }
     ],
     "name": "bar_txt"
    },
    {
     "keyframes": [
      {
       "ref": "~ButtonPlus",
       "tweened": false,
       "duration": 1,
       "index": 0,
       "loc": [
        77.5,
        0
       ]
      }
     ],
     "name": "ButtonPlusWOOD"
    }
   ],
   "id": "~INFO_Wood"
  },
  {
   "layers": [
    {
     "keyframes": [
      {
       "ref": "_bg_gauge",
       "pivot": [
        60,
        19
       ],
       "tweened": false,
       "duration": 1,
       "index": 0
      }
     ],
     "name": "_bg_gauge"
    },
    {
     "keyframes": [
      {
       "ref": "_gauge_buildingTime",
       "pivot": [
        60,
        19
       ],
       "tweened": false,
       "duration": 1,
       "index": 0
      }
     ],
     "name": "_gauge"
    },
    {
     "keyframes": [
      {
       "ref": "_time",
       "tweened": false,
       "duration": 1,
       "index": 0,
       "loc": [
        1.125,
        0.55
       ]
      }
     ],
     "name": "_time"
    }
   ],
   "id": "~isBuilding_gauge"
  },
  {
   "layers": [
    {
     "keyframes": [
      {
       "ref": "_bg_gauge",
       "pivot": [
        60,
        19
       ],
       "tweened": false,
       "duration": 1,
       "index": 0
      }
     ],
     "name": "_bg_gauge"
    },
    {
     "keyframes": [
      {
       "pivot": [
        60,
        19
       ],
       "index": 0,
       "loc": [
        0,
        -0.3
       ],
       "ref": "_gauge",
       "tweened": false,
       "duration": 1
      }
     ],
     "name": "_gauge"
    },
    {
     "keyframes": [
      {
       "ref": "_time",
       "tweened": false,
       "duration": 1,
       "index": 0,
       "loc": [
        1.125,
        0.55
       ]
      }
     ],
     "name": "_time"
    }
   ],
   "id": "~isProducing_gauge"
  }
 ],
 "frameRate": 24
}